.VERSION
AUTHORS.rst
CONTRIBUTING.rst
HISTORY.rst
LICENSE
MANIFEST.in
Pipfile
Pipfile.lock
README.rst
USAGE.rst
dev-requirements.txt
requirements.txt
setup.cfg
setup.py
docs/Makefile
docs/authors.rst
docs/conf.py
docs/contributing.rst
docs/history.rst
docs/index.rst
docs/installation.rst
docs/modules.rst
docs/notifierlib.channels.rst
docs/notifierlib.rst
docs/readme.rst
docs/usage.rst
notifierlib/.VERSION
notifierlib/AUTHORS.rst
notifierlib/CONTRIBUTING.rst
notifierlib/HISTORY.rst
notifierlib/LICENSE
notifierlib/Pipfile
notifierlib/Pipfile.lock
notifierlib/README.rst
notifierlib/USAGE.rst
notifierlib/__init__.py
notifierlib/_version.py
notifierlib/dev-requirements.txt
notifierlib/notifierlib.py
notifierlib/notifierlibexceptions.py
notifierlib/requirements.txt
notifierlib.egg-info/PKG-INFO
notifierlib.egg-info/SOURCES.txt
notifierlib.egg-info/dependency_links.txt
notifierlib.egg-info/not-zip-safe
notifierlib.egg-info/requires.txt
notifierlib.egg-info/top_level.txt
notifierlib/channels/__init__.py
notifierlib/channels/email.py
notifierlib/channels/jabber.py
notifierlib/channels/mattermost.py
notifierlib/channels/slack.py
notifierlib/channels/stdout.py
notifierlib/channels/telegram_.py