Metadata-Version: 2.1
Name: notifierlib
Version: 1.0.0
Summary: A library that implements a kind of fan-out pattern, sending messages to very different endpoints. Extendable through the implementation of custom Channels. 
Home-page: https://github.com/costastf/notifierlib
Author: Costas Tyfoxylos
Author-email: costas.tyf@gmail.com
License: MIT
Keywords: notifierlib
Platform: UNKNOWN
Classifier: Development Status :: 4 - Beta
Classifier: Intended Audience :: Developers
Classifier: License :: OSI Approved :: MIT License
Classifier: Natural Language :: English
Classifier: Programming Language :: Python :: 3.7
License-File: LICENSE
License-File: AUTHORS.rst
